{
  "schema": "tokenoskobi_hunter_alert_v1_schema_contract_plan_noapi_v1",
  "mode": "PLAN_ONLY_NOAPI",
  "status": "SCHEMA_PLAN_NOT_ACTIVE_RUNTIME",
  "payload_type": "HUNTER_ALERT_V1",
  "parent_protocol": "CMP_V1",
  "source_army": "HUNTER_ARMY",
  "target_army": "PROSECUTOR_ARMY",
  "purpose": "first_hot_path_alert_language_for_readonly_evidence_runtime",
  "payload_shape": {
    "flat_payload_required": true,
    "nested_payload_forbidden": true,
    "optional_hot_path_fields_forbidden": true,
    "payload_max_bytes": 4096,
    "evidence_body_forbidden": true,
    "evidence_refs_only": true,
    "raw_html_forbidden": true,
    "large_json_forbidden": true,
    "secret_material_forbidden": true,
    "wallet_payload_forbidden": true,
    "live_execution_payload_forbidden": true
  },
  "temporal_aliasing_guard": {
    "event_time_ns_required": true,
    "observed_at_ns_required": true,
    "created_at_ns_required": true,
    "market_regime_id_required": true,
    "market_regime_version_required": true,
    "context_version_required": true,
    "stale_if_regime_mismatch": true,
    "stale_if_context_version_mismatch": true,
    "stale_if_event_time_expired": true,
    "processing_regime_must_match_message_regime": true,
    "stale_context_message_class": "STALE_CONTEXT_MESSAGE",
    "stale_time_message_class": "STALE_TIME_MESSAGE",
    "stale_message_quarantine_required": true
  },
  "trust_cost_guard": {
    "source_trust_score_required": true,
    "source_trust_tier_required": true,
    "raw_cost_units_required": true,
    "trust_adjusted_cost_units_required": true,
    "low_trust_source_virtual_cost_multiplier_required": true,
    "cheap_but_low_trust_cannot_win_by_cost_alone": true,
    "trust_cost_degraded_source_class": "TRUST_COST_DEGRADED_SOURCE",
    "cost_selection_must_consider_trust": true,
    "low_trust_source_requires_higher_evidence_count": true
  },
  "evidence_ref_integrity_guard": {
    "evidence_ref_count_required": true,
    "evidence_ref_count_max": 8,
    "evidence_id_required": true,
    "evidence_hash_required": true,
    "evidence_hash_algorithm_required": true,
    "evidence_hash_algorithm": "SHA256",
    "evidence_owner_binding_required": true,
    "evidence_scope_binding_required": true,
    "evidence_ref_hash_check_required": true,
    "prosecutor_must_recompute_evidence_hash_on_fetch": true,
    "evidence_hash_mismatch_is_tampering": true,
    "evidence_tampering_is_not_protocol_violation": true,
    "evidence_tampering_class": "EVIDENCE_TAMPERING",
    "evidence_tampering_global_block_review_required": true,
    "evidence_tampering_source_trust_hard_penalty_required": true
  },
  "required_flat_payload_fields": [
    "payload_schema_version",
    "alert_id",
    "asset_uid",
    "chain_id",
    "chain_slug",
    "token_address_norm",
    "pair_or_pool_id",
    "discovery_source_id",
    "discovery_source_type",
    "event_time_ns",
    "observed_at_ns",
    "created_at_ns",
    "expires_at_ns",
    "ttl_sec",
    "market_regime_id",
    "market_regime_version",
    "context_version",
    "registry_version",
    "registry_sha",
    "source_trust_score",
    "source_trust_tier",
    "raw_cost_units",
    "trust_adjusted_cost_units",
    "low_trust_cost_multiplier",
    "shadow_signal_score",
    "interestingness_score",
    "alpha_priority_bypass_requested",
    "alpha_priority_bypass_reason_code",
    "evidence_ref_count",
    "evidence_hash_algorithm",
    "evidence_id_01",
    "evidence_hash_01",
    "evidence_owner_01",
    "evidence_scope_01",
    "risk_flag_bitmap",
    "suspicion_class",
    "route_hint",
    "live_execution_forbidden"
  ],
  "evidence_slot_policy": {
    "slot_count": 8,
    "slot_field_pattern": [
      "evidence_id_XX",
      "evidence_hash_XX",
      "evidence_owner_XX",
      "evidence_scope_XX"
    ],
    "unused_slots_must_be_empty_string": true,
    "if_evidence_id_present_hash_required": true,
    "if_hash_present_id_required": true,
    "payload_invalid_if_hash_pair_missing": true
  },
  "score_bounds": {
    "source_trust_score_min": 0.0,
    "source_trust_score_max": 1.0,
    "shadow_signal_score_min": 0.0,
    "shadow_signal_score_max": 1.0,
    "interestingness_score_min": 0.0,
    "interestingness_score_max": 1.0,
    "raw_cost_units_min": 0,
    "raw_cost_units_max": 100,
    "trust_adjusted_cost_units_min": 0,
    "trust_adjusted_cost_units_max": 1000,
    "low_trust_cost_multiplier_min": 1.0,
    "low_trust_cost_multiplier_max": 20.0
  },
  "allowed_route_hints": [
    "WATCH",
    "PROSECUTOR_VALIDATE",
    "DEEP_SCAN_REQUEST",
    "REVIEW_REQUEST",
    "QUARANTINE"
  ],
  "forbidden_route_hints": [
    "BUY",
    "SELL",
    "EXECUTE",
    "LIVE_TRADE",
    "WALLET_SIGN",
    "PATCH",
    "APPLY"
  ],
  "classification_outputs": [
    "HUNTER_ALERT_ACCEPTED",
    "STALE_CONTEXT_MESSAGE",
    "STALE_TIME_MESSAGE",
    "TRUST_COST_DEGRADED_SOURCE",
    "EVIDENCE_TAMPERING",
    "PROTOCOL_VIOLATION",
    "QUARANTINE",
    "WAIT_EVIDENCE_ASYNC",
    "STALE_EVIDENCE_PENDING",
    "ASYNC_EVIDENCE_FETCH_FAILED",
    "EVIDENCE_CACHE_HIT_VERIFIED",
    "EVIDENCE_CACHE_MISS_QUEUED"
  ],
  "validation_order": [
    "CHECK_CMP_HEADER_VALIDATED",
    "CHECK_PAYLOAD_TYPE_HUNTER_ALERT_V1",
    "CHECK_PAYLOAD_FLAT_NO_NESTED",
    "CHECK_PAYLOAD_MAX_BYTES_4096",
    "CHECK_REQUIRED_FIELDS",
    "CHECK_NO_UNKNOWN_FIELDS",
    "CHECK_EVENT_TIME_NS",
    "CHECK_TTL_AND_EXPIRES_AT",
    "CHECK_MARKET_REGIME_ID",
    "CHECK_CONTEXT_VERSION",
    "CHECK_REGIME_MATCH_AT_PROCESSING",
    "CHECK_SOURCE_TRUST_SCORE",
    "CHECK_TRUST_ADJUSTED_COST",
    "CHECK_LOW_TRUST_COST_MULTIPLIER",
    "CHECK_EVIDENCE_REF_COUNT",
    "CHECK_EVIDENCE_ID_HASH_PAIRS",
    "CHECK_EVIDENCE_OWNER_SCOPE_BINDING",
    "CHECK_FORBIDDEN_ROUTE_HINTS",
    "CHECK_LIVE_EXECUTION_FORBIDDEN",
    "ROUTE_TO_PROSECUTOR_OR_QUARANTINE",
    "CHECK_EVIDENCE_CACHE_KEY",
    "CHECK_LOCAL_EVIDENCE_CACHE_FIRST",
    "IF_CACHE_MISS_QUEUE_ASYNC_EVIDENCE_FETCH",
    "DO_NOT_SYNC_WAIT_ON_CACHE_MISS",
    "SET_WAIT_EVIDENCE_ASYNC_STATE",
    "CHECK_PENDING_EVIDENCE_TTL",
    "RECHECK_REGIME_CONTEXT_TTL_ON_EVIDENCE_FETCH_RESULT",
    "VERIFY_EVIDENCE_HASH_BEFORE_DECISION",
    "QUARANTINE_STALE_EVIDENCE_PENDING",
    "BLOCK_DECISION_UNTIL_EVIDENCE_VERIFIED"
  ],
  "authority_locks": {
    "trade_authority": false,
    "wallet_authority": false,
    "live_trade": false,
    "auto_apply": false,
    "auto_patch": false,
    "hard_block_bypass": false,
    "hunter_alert_can_only_route_to_prosecutor_review_or_quarantine": true,
    "hunter_alert_cannot_create_decision": true,
    "hunter_alert_cannot_execute": true,
    "message_bus_live_execution_forbidden": true,
    "decision_forbidden_until_evidence_verified": true,
    "cache_miss_cannot_create_decision": true,
    "async_fetch_failure_cannot_create_decision": true
  },
  "contract_version": "v1.1_async_evidence_handshake",
  "async_evidence_handshake": {
    "cache_first_evidence_lookup": true,
    "evidence_cache_key_required": true,
    "evidence_cache_key_fields": [
      "evidence_id",
      "evidence_hash",
      "evidence_owner",
      "evidence_scope",
      "registry_sha",
      "context_version"
    ],
    "evidence_cache_lookup_first": true,
    "evidence_cache_hash_verify_required": true,
    "async_evidence_fetch_queue_required": true,
    "prosecutor_no_sync_wait_on_cache_miss": true,
    "prosecutor_main_path_must_not_block_on_evidence_fetch": true,
    "wait_evidence_async_state_required": true,
    "wait_evidence_async_state": "WAIT_EVIDENCE_ASYNC",
    "pending_evidence_ttl_required": true,
    "pending_evidence_ttl_sec": 30,
    "stale_evidence_pending_class": "STALE_EVIDENCE_PENDING",
    "stale_evidence_pending_quarantine_required": true,
    "max_pending_evidence_per_source_required": true,
    "max_pending_evidence_per_source": 128,
    "max_pending_evidence_per_asset_required": true,
    "max_pending_evidence_per_asset": 64,
    "evidence_fetch_result_must_recheck_regime_id": true,
    "evidence_fetch_result_must_recheck_context_version": true,
    "evidence_fetch_result_must_recheck_ttl": true,
    "evidence_fetch_result_must_recheck_hash": true,
    "decision_forbidden_until_evidence_verified": true,
    "cache_miss_cannot_create_decision": true,
    "async_fetch_failure_cannot_create_decision": true,
    "evidence_hash_mismatch_remains_evidence_tampering": true,
    "pending_queue_rate_limit_required": true,
    "pending_queue_overflow_policy": "QUARANTINE_LOW_PRIORITY_PENDING_ALERTS",
    "large_evidence_fetch_hot_path_forbidden": true
  },
  "red_team_async_evidence_fix": {
    "finding": "evidence_runtime_lag_can_block_prosecutor_or_create_pending_lag",
    "fix": "cache_first_lookup_async_fetch_no_sync_wait_pending_ttl_quarantine",
    "applied": true
  }
}
