{
  "api_calls": 0,
  "db_write": false,
  "degradation_lifecycle": [
    "NORMAL",
    "DEGRADED",
    "SURVIVAL",
    "MAINTENANCE_MODE",
    "FAIL_CLOSED"
  ],
  "duration_plan": {
    "event_driven": true,
    "logical_time_only": true,
    "minimum_hours": 48,
    "mode": "PAPER_RUNTIME_OBSERVE_FULL_LOAD",
    "target_hours": 72
  },
  "era": "ERA19",
  "four_g_gate": {
    "economy": "LOG_ROTATION_AND_LEDGER_PRIORITY",
    "power": "STABILITY_AND_AUTONOMY_CERTIFICATION",
    "security": "RECOVERY_AND_LEDGER_INTEGRITY_REQUIRED",
    "speed": "EVENT_DRIVEN_LONG_RUN_NO_IDLE_SPIN"
  },
  "gate": "GATE02",
  "ledger_protection": {
    "append_only": true,
    "diff_reporting": true,
    "gsn_required": true,
    "immutable_seal_required": true,
    "ledger_integrity_verification": true,
    "triple_ledger_priority": [
      "DECISION",
      "PAPER",
      "SHADOW",
      "DRIFT_LOG"
    ],
    "wal_required": true
  },
  "live_trade": false,
  "log_policy": {
    "decision_ledger_never_degraded": true,
    "disk_pressure_action": "DEGRADE_LOW_PRIORITY_LOGS_FIRST",
    "drift_log_degradation_allowed": true,
    "log_rotation_required": true
  },
  "name": "LONG_RUN_STABILITY_PLAN",
  "next": "ERA19_GATE02B_LONG_RUN_STABILITY_DRYRUN_NOAPI",
  "observe_mode": {
    "observe_load_equals_normal_load": true,
    "output_authority_disabled": true,
    "paper_runtime_full_load": true
  },
  "order_create": false,
  "panel_write": false,
  "paper_trade": false,
  "resource_autonomy_tests": {
    "disk_pressure": true,
    "memory_pressure": true,
    "network_loss": true,
    "process_kill": true,
    "recovery_snapshot": true,
    "restart_recovery": true,
    "rpc_timeout": true,
    "service_crash": true
  },
  "service_restart": false,
  "signing": false,
  "stability_checks": {
    "cpu_drift": true,
    "deadlock_watch": true,
    "fd_count": true,
    "latency_drift": true,
    "ledger_growth": true,
    "log_bloat": true,
    "memory_leak": true,
    "queue_backlog": true,
    "thread_count": true
  },
  "status": "PLAN_ONLY_NOAPI",
  "timer_change": false,
  "ts_utc": "2026-06-29T20:24:37Z",
  "wallet": false
}
