{
  "phase": "ICON_REGISTRY_BUILD_PLAN_NOAPI",
  "started_at": "2026-05-20 01:27:28",
  "final_gate": "PASS",
  "safety": {
    "api_calls": 0,
    "external_network_calls": 0,
    "db_mutation": false,
    "active_panel_mutation": false,
    "asset_mutation": false,
    "registry_mutation": false,
    "plan_only": true
  },
  "summary": {
    "registry_entries": 77,
    "expected_total": 77,
    "group_counts": {
      "komuta_merkezi": 8,
      "haber_akis_merkezi": 11,
      "onchain_veri_merkezi": 9,
      "balina_takip_merkezi": 8,
      "teknik_analiz_merkezi": 8,
      "risk_guvenlik_merkezi": 8,
      "yasam_destek_merkezi": 7,
      "sistem_kontrol_merkezi": 14,
      "pilot_modlari": 2,
      "global_durumlar": 2
    },
    "type_counts": {
      "master": 8,
      "module": 65,
      "pilot_mode": 2,
      "global_state": 2
    },
    "main_center_master_count": 8,
    "errors": [],
    "warnings": []
  },
  "registry_candidate_path": "/root/tokenoskobi_clean_v1/data/icon_registry_candidate_plan_noapi.json",
  "next_recommended_phase": "ICON_REGISTRY_BUILD_APPLY_AFTER_APPROVAL",
  "approval_phrase": "ICON registry build apply için onay veriyorum"
}