{
  "phase": "PANEL_ICON_CARD_MASK_STYLE_PLAN_NOAPI",
  "started_at": "2026-05-20 10:52:22",
  "final_gate": "PASS",
  "safety": {
    "api_calls": 0,
    "external_network_calls": 0,
    "db_mutation": false,
    "active_panel_mutation": false,
    "asset_mutation": false,
    "candidate_bind": false,
    "original_overwrite": false,
    "binding_mutation": false,
    "preview_mutation": false,
    "style_mutation": false,
    "plan_only": true,
    "source_files_unchanged": true,
    "trade_execution_allowed": false,
    "paper_trade_open_allowed": false
  },
  "sources": {
    "reject_json": {
      "path": "/root/tokenoskobi_clean_v1/data/panel_bound_icon_visual_fit_candidate_reject_hold_noapi.json",
      "sha256": "4083306e9bb567e4dbf40d34a04c0455cb2e904568b0970b15c78e0f103b8af6"
    },
    "reject_rows": {
      "path": "/root/tokenoskobi_clean_v1/data/panel_bound_icon_visual_fit_candidate_reject_hold_rows_noapi.jsonl",
      "sha256": "4d7883f6b9d7b7274605fbb180184a5852e073a19f4b59e847c063644e4c011b"
    },
    "icon_binding": {
      "path": "/root/tokenoskobi_clean_v1/panel_assets/panel_icon_binding_v1.json",
      "sha256": "6a444713434d6a6c59ad341448d8bdb8ac3bd96e108ce5f55d230cf2b5b29362"
    },
    "bound_preview_json": {
      "path": "/root/tokenoskobi_clean_v1/data/panel_bound_preview_build_after_approval.json",
      "sha256": "7c826f54e8b379eba27a22c6b49c577e60b136b0c72c15a04fc3df4e9aa44144"
    }
  },
  "summary": {
    "target_problem_rows": 8,
    "expected_problem_rows": 8,
    "style_variants": 3,
    "recommended_variant": "circle_mask_v1",
    "active_binding_has_fit_v1": false,
    "missing_original_icons": 0,
    "group_counts": {
      "komuta_merkezi": 5,
      "yasam_destek_merkezi": 3
    },
    "planned_preview_port": 8107,
    "bound_preview_url": "http://159.195.74.132:8105/",
    "rejected_compare_url": "http://159.195.74.132:8106/",
    "errors": [],
    "warnings": []
  },
  "style_variants": [
    {
      "variant_key": "circle_mask_v1",
      "label": "Dairesel maske / orijinal ikon",
      "description": "Orijinal ikon dosyasını değiştirmeden kare matte köşeleri circular overflow ile gizler.",
      "recommended": true,
      "css": {
        "frame_width_mobile": "74px",
        "frame_height_mobile": "74px",
        "frame_width_desktop": "82px",
        "frame_height_desktop": "82px",
        "border_radius": "999px",
        "overflow": "hidden",
        "background": "#07111f",
        "img_width": "100%",
        "img_height": "100%",
        "object_fit": "cover",
        "transform": "scale(1.10)"
      }
    },
    {
      "variant_key": "rounded_square_dark_v1",
      "label": "Koyu rounded-square konteyner",
      "description": "Dairesel crop agresif gelirse koyu rounded container ile gri köşeleri yumuşatır.",
      "recommended": false,
      "css": {
        "frame_width_mobile": "78px",
        "frame_height_mobile": "78px",
        "border_radius": "22px",
        "overflow": "hidden",
        "background": "#07111f",
        "img_object_fit": "cover",
        "transform": "scale(1.06)"
      }
    },
    {
      "variant_key": "soft_inset_shadow_v1",
      "label": "Soft inset shadow",
      "description": "Gri zemin tamamen gitmese bile panelle bütünleştirir.",
      "recommended": false,
      "css": {
        "box_shadow": "inset 0 0 24px rgba(7,17,31,.80), 0 12px 28px rgba(0,0,0,.35)",
        "border_radius": "28px",
        "overflow": "hidden"
      }
    }
  ],
  "preview_policy": {
    "preview_root": "/root/tokenoskobi_clean_v1/panel_previews/icon_card_mask_style_preview_v1",
    "preview_port": 8107,
    "preview_url": "http://159.195.74.132:8107/",
    "source": "original active icon_binding icons only",
    "do_not_use": "fit_v1 rejected candidates",
    "compare_modes": [
      "current_original_card",
      "circle_mask_v1",
      "rounded_square_dark_v1"
    ],
    "no_asset_copy": true,
    "asset_symlink_ok": true,
    "active_8096_forbidden": true,
    "db_api_forbidden": true
  },
  "target_rows": [
    {
      "node_key": "komuta_merkezi.acik_pozisyonlar",
      "label_tr": "Açık Pozisyonlar",
      "group": "komuta_merkezi",
      "route_path": "/merkez/komuta/acik-pozisyonlar",
      "source_icon_128": "panel_assets/icons_panel_128/komuta_merkezi/acik_pozisyonlar_128.jpg",
      "source_icon_384": "panel_assets/icons_panel_384/komuta_merkezi/acik_pozisyonlar_384.jpg",
      "source_icon_1024": "panel_assets/icons_panel_1024_normalized/komuta_merkezi/acik_pozisyonlar_1024.jpg",
      "rejected_candidate_384": "panel_assets/icon_fit_candidates/icons_panel_384_fit_v1/komuta_merkezi/acik_pozisyonlar_fit_v1_384.jpg",
      "visual_problem": "light/krem square matte visible around circular artwork",
      "planned_solution": "CSS_CARD_LEVEL_CIRCULAR_MASK_USING_ORIGINAL_ICON",
      "style_scope": "preview_only_first",
      "asset_overwrite": false,
      "candidate_bind": false,
      "active_8096_allowed": false,
      "css_plan": {
        "wrapper_class": "iconMaskFrame",
        "img_class": "maskedIconOriginal",
        "wrapper_border_radius": "999px",
        "wrapper_overflow": "hidden",
        "wrapper_background": "#07111f",
        "wrapper_box_shadow": "inset 0 0 0 1px rgba(148,163,184,.20), 0 12px 28px rgba(0,0,0,.35)",
        "img_object_fit": "cover",
        "img_transform": "scale(1.10)",
        "img_border_radius": "999px",
        "reason": "Hide square matte corners at card level without modifying image file or shrinking artwork."
      }
    },
    {
      "node_key": "komuta_merkezi.aksiyon_gecmisi",
      "label_tr": "Aksiyon Geçmişi",
      "group": "komuta_merkezi",
      "route_path": "/merkez/komuta/aksiyon-gecmisi",
      "source_icon_128": "panel_assets/icons_panel_128/komuta_merkezi/aksiyon_gecmisi_128.jpg",
      "source_icon_384": "panel_assets/icons_panel_384/komuta_merkezi/aksiyon_gecmisi_384.jpg",
      "source_icon_1024": "panel_assets/icons_panel_1024_normalized/komuta_merkezi/aksiyon_gecmisi_1024.jpg",
      "rejected_candidate_384": "panel_assets/icon_fit_candidates/icons_panel_384_fit_v1/komuta_merkezi/aksiyon_gecmisi_fit_v1_384.jpg",
      "visual_problem": "light/krem square matte visible around circular artwork",
      "planned_solution": "CSS_CARD_LEVEL_CIRCULAR_MASK_USING_ORIGINAL_ICON",
      "style_scope": "preview_only_first",
      "asset_overwrite": false,
      "candidate_bind": false,
      "active_8096_allowed": false,
      "css_plan": {
        "wrapper_class": "iconMaskFrame",
        "img_class": "maskedIconOriginal",
        "wrapper_border_radius": "999px",
        "wrapper_overflow": "hidden",
        "wrapper_background": "#07111f",
        "wrapper_box_shadow": "inset 0 0 0 1px rgba(148,163,184,.20), 0 12px 28px rgba(0,0,0,.35)",
        "img_object_fit": "cover",
        "img_transform": "scale(1.10)",
        "img_border_radius": "999px",
        "reason": "Hide square matte corners at card level without modifying image file or shrinking artwork."
      }
    },
    {
      "node_key": "komuta_merkezi.canli_karar",
      "label_tr": "Canlı Karar",
      "group": "komuta_merkezi",
      "route_path": "/merkez/komuta/canli-karar",
      "source_icon_128": "panel_assets/icons_panel_128/komuta_merkezi/canli_karar_128.jpg",
      "source_icon_384": "panel_assets/icons_panel_384/komuta_merkezi/canli_karar_384.jpg",
      "source_icon_1024": "panel_assets/icons_panel_1024_normalized/komuta_merkezi/canli_karar_1024.jpg",
      "rejected_candidate_384": "panel_assets/icon_fit_candidates/icons_panel_384_fit_v1/komuta_merkezi/canli_karar_fit_v1_384.jpg",
      "visual_problem": "light/krem square matte visible around circular artwork",
      "planned_solution": "CSS_CARD_LEVEL_CIRCULAR_MASK_USING_ORIGINAL_ICON",
      "style_scope": "preview_only_first",
      "asset_overwrite": false,
      "candidate_bind": false,
      "active_8096_allowed": false,
      "css_plan": {
        "wrapper_class": "iconMaskFrame",
        "img_class": "maskedIconOriginal",
        "wrapper_border_radius": "999px",
        "wrapper_overflow": "hidden",
        "wrapper_background": "#07111f",
        "wrapper_box_shadow": "inset 0 0 0 1px rgba(148,163,184,.20), 0 12px 28px rgba(0,0,0,.35)",
        "img_object_fit": "cover",
        "img_transform": "scale(1.10)",
        "img_border_radius": "999px",
        "reason": "Hide square matte corners at card level without modifying image file or shrinking artwork."
      }
    },
    {
      "node_key": "komuta_merkezi.paper_trade_ozeti",
      "label_tr": "Paper Trade Özeti",
      "group": "komuta_merkezi",
      "route_path": "/merkez/komuta/paper-trade-ozeti",
      "source_icon_128": "panel_assets/icons_panel_128/komuta_merkezi/paper_trade_ozeti_128.jpg",
      "source_icon_384": "panel_assets/icons_panel_384/komuta_merkezi/paper_trade_ozeti_384.jpg",
      "source_icon_1024": "panel_assets/icons_panel_1024_normalized/komuta_merkezi/paper_trade_ozeti_1024.jpg",
      "rejected_candidate_384": "panel_assets/icon_fit_candidates/icons_panel_384_fit_v1/komuta_merkezi/paper_trade_ozeti_fit_v1_384.jpg",
      "visual_problem": "light/krem square matte visible around circular artwork",
      "planned_solution": "CSS_CARD_LEVEL_CIRCULAR_MASK_USING_ORIGINAL_ICON",
      "style_scope": "preview_only_first",
      "asset_overwrite": false,
      "candidate_bind": false,
      "active_8096_allowed": false,
      "css_plan": {
        "wrapper_class": "iconMaskFrame",
        "img_class": "maskedIconOriginal",
        "wrapper_border_radius": "999px",
        "wrapper_overflow": "hidden",
        "wrapper_background": "#07111f",
        "wrapper_box_shadow": "inset 0 0 0 1px rgba(148,163,184,.20), 0 12px 28px rgba(0,0,0,.35)",
        "img_object_fit": "cover",
        "img_transform": "scale(1.10)",
        "img_border_radius": "999px",
        "reason": "Hide square matte corners at card level without modifying image file or shrinking artwork."
      }
    },
    {
      "node_key": "komuta_merkezi.sl_tp_durumu",
      "label_tr": "SL / TP Durumu",
      "group": "komuta_merkezi",
      "route_path": "/merkez/komuta/sl-tp-durumu",
      "source_icon_128": "panel_assets/icons_panel_128/komuta_merkezi/sl_tp_durumu_128.jpg",
      "source_icon_384": "panel_assets/icons_panel_384/komuta_merkezi/sl_tp_durumu_384.jpg",
      "source_icon_1024": "panel_assets/icons_panel_1024_normalized/komuta_merkezi/sl_tp_durumu_1024.jpg",
      "rejected_candidate_384": "panel_assets/icon_fit_candidates/icons_panel_384_fit_v1/komuta_merkezi/sl_tp_durumu_fit_v1_384.jpg",
      "visual_problem": "light/krem square matte visible around circular artwork",
      "planned_solution": "CSS_CARD_LEVEL_CIRCULAR_MASK_USING_ORIGINAL_ICON",
      "style_scope": "preview_only_first",
      "asset_overwrite": false,
      "candidate_bind": false,
      "active_8096_allowed": false,
      "css_plan": {
        "wrapper_class": "iconMaskFrame",
        "img_class": "maskedIconOriginal",
        "wrapper_border_radius": "999px",
        "wrapper_overflow": "hidden",
        "wrapper_background": "#07111f",
        "wrapper_box_shadow": "inset 0 0 0 1px rgba(148,163,184,.20), 0 12px 28px rgba(0,0,0,.35)",
        "img_object_fit": "cover",
        "img_transform": "scale(1.10)",
        "img_border_radius": "999px",
        "reason": "Hide square matte corners at card level without modifying image file or shrinking artwork."
      }
    },
    {
      "node_key": "yasam_destek_merkezi.klinik",
      "label_tr": "Klinik",
      "group": "yasam_destek_merkezi",
      "route_path": "/merkez/yasam-destek/klinik",
      "source_icon_128": "panel_assets/icons_panel_128/yasam_destek_merkezi/klinik_128.jpg",
      "source_icon_384": "panel_assets/icons_panel_384/yasam_destek_merkezi/klinik_384.jpg",
      "source_icon_1024": "panel_assets/icons_panel_1024_normalized/yasam_destek_merkezi/klinik_1024.jpg",
      "rejected_candidate_384": "panel_assets/icon_fit_candidates/icons_panel_384_fit_v1/yasam_destek_merkezi/klinik_fit_v1_384.jpg",
      "visual_problem": "light/krem square matte visible around circular artwork",
      "planned_solution": "CSS_CARD_LEVEL_CIRCULAR_MASK_USING_ORIGINAL_ICON",
      "style_scope": "preview_only_first",
      "asset_overwrite": false,
      "candidate_bind": false,
      "active_8096_allowed": false,
      "css_plan": {
        "wrapper_class": "iconMaskFrame",
        "img_class": "maskedIconOriginal",
        "wrapper_border_radius": "999px",
        "wrapper_overflow": "hidden",
        "wrapper_background": "#07111f",
        "wrapper_box_shadow": "inset 0 0 0 1px rgba(148,163,184,.20), 0 12px 28px rgba(0,0,0,.35)",
        "img_object_fit": "cover",
        "img_transform": "scale(1.10)",
        "img_border_radius": "999px",
        "reason": "Hide square matte corners at card level without modifying image file or shrinking artwork."
      }
    },
    {
      "node_key": "yasam_destek_merkezi.morg",
      "label_tr": "Morg",
      "group": "yasam_destek_merkezi",
      "route_path": "/merkez/yasam-destek/morg",
      "source_icon_128": "panel_assets/icons_panel_128/yasam_destek_merkezi/morg_128.jpg",
      "source_icon_384": "panel_assets/icons_panel_384/yasam_destek_merkezi/morg_384.jpg",
      "source_icon_1024": "panel_assets/icons_panel_1024_normalized/yasam_destek_merkezi/morg_1024.jpg",
      "rejected_candidate_384": "panel_assets/icon_fit_candidates/icons_panel_384_fit_v1/yasam_destek_merkezi/morg_fit_v1_384.jpg",
      "visual_problem": "light/krem square matte visible around circular artwork",
      "planned_solution": "CSS_CARD_LEVEL_CIRCULAR_MASK_USING_ORIGINAL_ICON",
      "style_scope": "preview_only_first",
      "asset_overwrite": false,
      "candidate_bind": false,
      "active_8096_allowed": false,
      "css_plan": {
        "wrapper_class": "iconMaskFrame",
        "img_class": "maskedIconOriginal",
        "wrapper_border_radius": "999px",
        "wrapper_overflow": "hidden",
        "wrapper_background": "#07111f",
        "wrapper_box_shadow": "inset 0 0 0 1px rgba(148,163,184,.20), 0 12px 28px rgba(0,0,0,.35)",
        "img_object_fit": "cover",
        "img_transform": "scale(1.10)",
        "img_border_radius": "999px",
        "reason": "Hide square matte corners at card level without modifying image file or shrinking artwork."
      }
    },
    {
      "node_key": "yasam_destek_merkezi.otopsi",
      "label_tr": "Otopsi",
      "group": "yasam_destek_merkezi",
      "route_path": "/merkez/yasam-destek/otopsi",
      "source_icon_128": "panel_assets/icons_panel_128/yasam_destek_merkezi/otopsi_128.jpg",
      "source_icon_384": "panel_assets/icons_panel_384/yasam_destek_merkezi/otopsi_384.jpg",
      "source_icon_1024": "panel_assets/icons_panel_1024_normalized/yasam_destek_merkezi/otopsi_1024.jpg",
      "rejected_candidate_384": "panel_assets/icon_fit_candidates/icons_panel_384_fit_v1/yasam_destek_merkezi/otopsi_fit_v1_384.jpg",
      "visual_problem": "light/krem square matte visible around circular artwork",
      "planned_solution": "CSS_CARD_LEVEL_CIRCULAR_MASK_USING_ORIGINAL_ICON",
      "style_scope": "preview_only_first",
      "asset_overwrite": false,
      "candidate_bind": false,
      "active_8096_allowed": false,
      "css_plan": {
        "wrapper_class": "iconMaskFrame",
        "img_class": "maskedIconOriginal",
        "wrapper_border_radius": "999px",
        "wrapper_overflow": "hidden",
        "wrapper_background": "#07111f",
        "wrapper_box_shadow": "inset 0 0 0 1px rgba(148,163,184,.20), 0 12px 28px rgba(0,0,0,.35)",
        "img_object_fit": "cover",
        "img_transform": "scale(1.10)",
        "img_border_radius": "999px",
        "reason": "Hide square matte corners at card level without modifying image file or shrinking artwork."
      }
    }
  ],
  "next_recommended_phase": "PANEL_ICON_CARD_MASK_STYLE_PREVIEW_BUILD_AFTER_APPROVAL",
  "approval_phrase": "PANEL icon card mask style preview build için onay veriyorum"
}