{
  "phase":"PHASE51_BACKGROUND_INTELLIGENCE_OFFICER_PLAN_NOAPI",
  "status":"PLAN_ONLY",
  "purpose":"background_intelligence_officer",
  "duties":[
    "news_monitoring",
    "social_signal_monitoring",
    "launch_radar_monitoring",
    "ico_ido_airdrop_monitoring",
    "scam_tactic_monitoring",
    "mev_tactic_monitoring",
    "sandwich_tactic_monitoring",
    "rug_pattern_monitoring",
    "honeypot_pattern_monitoring",
    "dex_exploit_monitoring",
    "counter_intelligence_notes"
  ],
  "authority_locks":{
    "trade_authority":0,
    "ai_authority":0,
    "risk_override":0,
    "auto_policy_edit":0,
    "auto_block":0,
    "auto_apply":0,
    "wallet_authority":0,
    "signing_authority":0,
    "human_approval_required":true
  },
  "constitutional_gate_v1":{
    "speed_never_down":true,
    "security_never_down":true,
    "power_never_down":true,
    "denge_denge_denge":true,
    "hot_path_blocks":false,
    "risk_gate_weakens":false,
    "learning_blocks_execution":false,
    "news_social_can_never_convict_alone":true
  },
  "operating_model":{
    "read_only_first":true,
    "cache_first":true,
    "budget_guarded":true,
    "source_trust_required":true,
    "duplicate_filter_required":true,
    "manipulation_filter_required":true,
    "propaganda_filter_required":true,
    "low_trust_source_downrank":true
  },
  "next_safe_step":"PHASE51B_BACKGROUND_INTELLIGENCE_SCHEMA_PLAN_NOAPI",
  "final_gate":"PASS_PHASE51_BACKGROUND_INTELLIGENCE_OFFICER_PLAN_NOAPI",
  "created_utc":"20260622_101742"
}
