{
  "acceptance": [
    {
      "evidence": "C53B_001..C53B_004 present",
      "id": "A53D_001",
      "status": "ACCEPTED",
      "subject": "PHASE53B consumer/readmodel contracts"
    },
    {
      "evidence": "PASS + hard_failures=[]",
      "id": "A53D_002",
      "status": "ACCEPTED",
      "subject": "PHASE53C local post-audit"
    },
    {
      "evidence": "no trade/wallet/AI/auto-block/auto-apply",
      "id": "A53D_003",
      "status": "ACCEPTED",
      "subject": "authority boundary"
    },
    {
      "evidence": "NO_GIT_PUSH_UNTIL_PHASE53_FINAL",
      "id": "A53D_004",
      "status": "ACCEPTED",
      "subject": "push deferral"
    }
  ],
  "final_gate": "PASS_PHASE53D_CONSUMER_READMODEL_CONTRACT_LOCAL_ACCEPTANCE_NOAPI",
  "forbidden_diff": "",
  "git": {
    "branch": "main",
    "expected": "58b3397",
    "head": "58b3397"
  },
  "hard_failures": [],
  "phase": "PHASE53D_CONSUMER_READMODEL_CONTRACT_LOCAL_ACCEPTANCE_NOAPI",
  "phase53b_sha256": "a62484a03276fdb43d3f4739f61fa5196de26b3ac54c1103456ebafa44011908",
  "phase53c_sha256": "5691c925fa5cc2c94cd99cf9c1029480f947fb4ec78cec810c8dfe990872449c",
  "protected_state": {
    "02_MANIFESTO.md": {
      "exists": true,
      "path": "02_MANIFESTO.md",
      "sha256": "ed8e4dab3502856eb002893ce40cdbb85ec7c2333d62d1103b965e4284f6f3ff",
      "size": 4493
    },
    "03_ROADMAP.md": {
      "exists": true,
      "path": "03_ROADMAP.md",
      "sha256": "1e9a0e3c7ee3c8169681191dd0a7bc2e08bc06202c7a34310c61865a4b246666",
      "size": 17438
    },
    "04_ALMANAC.md": {
      "exists": true,
      "path": "04_ALMANAC.md",
      "sha256": "e29fae0e71a5bbe670586c804abedefd48f8db0c5d14086f272f6efb1ea7b6e9",
      "size": 40133
    },
    "05_ATLAS.md": {
      "exists": true,
      "path": "05_ATLAS.md",
      "sha256": "5a95eaa783bda9a5ef504b42722332acd2c3db033bbf3bd5a6ae6b0d093c317d",
      "size": 20271
    },
    "active_panel_8096/current": {
      "exists": true,
      "path": "active_panel_8096/current",
      "type": "dir"
    },
    "data/tokenoskobi_clean_v1.sqlite": {
      "exists": true,
      "path": "data/tokenoskobi_clean_v1.sqlite",
      "sha256": "ad60d581491833c59d78c24d8b44d5280af3efd8cad4667c7b104e46b68f1ee5",
      "size": 5500928
    },
    "docs/canonical/PROJECT_HANDOFF.md": {
      "exists": true,
      "path": "docs/canonical/PROJECT_HANDOFF.md",
      "sha256": "55539bbbd63257af9e0d829b92904393194bd8f11c634de1d89170912702df38",
      "size": 28159
    },
    "docs/canonical/PROJECT_MASTER_STATE.md": {
      "exists": true,
      "path": "docs/canonical/PROJECT_MASTER_STATE.md",
      "sha256": "114942a4e5c5df849e1b99243e8166c1197e88b8c084d1b079699dc7dff28dd5",
      "size": 227351
    }
  },
  "push_policy": "NO_GIT_PUSH_UNTIL_PHASE53_FINAL",
  "safe_next_step": "PHASE53E_FINAL_PHASE_CLOSURE_DOC_UPDATE_PLAN_NOAPI",
  "ts": "2026-06-23T09:50:39.840447+00:00"
}