{"task":"RUNTIME_SLICE_08_POST_AUDIT_NOAPI","timestamp_utc":"20260629T065205Z","status":"PASS","final_gate":"PASS_RUNTIME_SLICE_08_POST_AUDIT_NOAPI","next":"RUNTIME_SLICE_08_GITHUB_SEAL_NOAPI","github_push":false,"module":"tools/runtime_provider_abstraction_v1.py","apply_json":"data/runtime_slice_08_provider_abstraction_local_apply_noapi.json","checks":{"module_exists":true,"module_py_compile":true,"apply_json_valid":true,"apply_jsonl_valid":true,"provider_count":5,"payg_count":2,"low_cost_count":3,"live_enabled_count":0,"read_only_count":5,"alchemy_premium_confirm_only":true,"low_cost_first":true,"cache_first_required":true,"provider_rotation_required":true,"critical_cross_check_multi_provider":true},"red_lines":{"noapi":true,"wallet":false,"private_key":false,"order_create":false,"live_trade":false,"runtime_binding":false,"runtime_apply":false,"api_call":false,"packet_emit":false,"db_write":false},"failures":[]}
