{
  "task": "V2_34C_FAST_LANE_POISONING_PROTECTION_PLAN_NOAPI",
  "contract": "ADVERSARIAL_CONFLICT_MARKER",
  "conflict_marker_required": true,
  "conflict_types": [
    "source_disagreement",
    "time_order_conflict",
    "same_event_different_token",
    "same_wallet_different_identity",
    "liquidity_signal_conflict",
    "owner_privilege_conflict",
    "news_onchain_conflict"
  ],
  "conflict_action": "downgrade_to_review_lane_and_preserve_observation",
  "execution_on_conflict_allowed": false
}
